django_mailbox_abstract/__init__.py
django_mailbox_abstract/admin.py
django_mailbox_abstract/apps.py
django_mailbox_abstract/google_utils.py
django_mailbox_abstract/models.py
django_mailbox_abstract/signals.py
django_mailbox_abstract/utils.py
django_mailbox_abstract/management/__init__.py
django_mailbox_abstract/management/commands/__init__.py
django_mailbox_abstract/management/commands/getmail.py
django_mailbox_abstract/management/commands/processincomingmessage.py
django_mailbox_abstract/management/commands/rebuildmessageattachments.py
django_mailbox_abstract/tests/__init__.py
django_mailbox_abstract/tests/base.py
django_mailbox_abstract/tests/settings.py
django_mailbox_abstract/tests/test_integration_imap.py
django_mailbox_abstract/tests/test_mailbox.py
django_mailbox_abstract/tests/test_message_flattening.py
django_mailbox_abstract/tests/test_process_email.py
django_mailbox_abstract/tests/test_processincomingmessage.py
django_mailbox_abstract/tests/test_transports.py
django_mailbox_abstract/transports/__init__.py
django_mailbox_abstract/transports/babyl.py
django_mailbox_abstract/transports/base.py
django_mailbox_abstract/transports/generic.py
django_mailbox_abstract/transports/gmail.py
django_mailbox_abstract/transports/imap.py
django_mailbox_abstract/transports/maildir.py
django_mailbox_abstract/transports/mbox.py
django_mailbox_abstract/transports/mh.py
django_mailbox_abstract/transports/mmdf.py
django_mailbox_abstract/transports/pop3.py
django_mailbox_abstract-4.8.1.3.dist-info/LICENSE
django_mailbox_abstract-4.8.1.3.dist-info/METADATA
django_mailbox_abstract-4.8.1.3.dist-info/WHEEL
django_mailbox_abstract-4.8.1.3.dist-info/top_level.txt
django_mailbox_abstract-4.8.1.3.dist-info/RECORD
